speex_noise_cpp.abi3.so
pyspeex_noise/__init__.py
pyspeex_noise/__main__.py
pyspeex_noise-2.0.0.dist-info/METADATA
pyspeex_noise-2.0.0.dist-info/WHEEL
pyspeex_noise-2.0.0.dist-info/top_level.txt
pyspeex_noise-2.0.0.dist-info/RECORD
pyspeex_noise-2.0.0.dist-info/licenses/LICENSE.md
