Metadata-Version: 2.4
Name: pyspeex-noise
Version: 2.0.0
Summary: Noise suppression and automatic gain with speex
Home-page: https://github.com/rhasspy/pyspeex-noise
Author: Michael Hansen
Author-email: mike@rhasspy.org
License: MIT
Requires-Python: >=3.9
License-File: LICENSE.md
Provides-Extra: dev
Requires-Dist: black; extra == "dev"
Requires-Dist: flake8; extra == "dev"
Requires-Dist: isort; extra == "dev"
Requires-Dist: mypy; extra == "dev"
Requires-Dist: pylint; extra == "dev"
Requires-Dist: pytest; extra == "dev"
Requires-Dist: build; extra == "dev"
Dynamic: license-file
Dynamic: provides-extra
